smashtheque/__init__.py
smashtheque/smashtheque.py
smashtheque-0.0.2.dist-info/LICENSE
smashtheque-0.0.2.dist-info/METADATA
smashtheque-0.0.2.dist-info/WHEEL
smashtheque-0.0.2.dist-info/top_level.txt
smashtheque-0.0.2.dist-info/RECORD
